README.md
setup.py
py_co_commit/__init__.py
py_co_commit.egg-info/PKG-INFO
py_co_commit.egg-info/SOURCES.txt
py_co_commit.egg-info/dependency_links.txt
py_co_commit.egg-info/entry_points.txt
py_co_commit.egg-info/top_level.txt