Metadata-Version: 2.1
Name: py-co-commit
Version: 0.1
Summary: An easy way to create a commit with multiple authors
Home-page: https://github.com/vincentdnl/py-co-commit.git
Author: Vincent Déniel
Author-email: vincentdnl@users.noreply.github.com
License: apache-2.0
Platform: UNKNOWN
